cwave/__init__.py
cwave/trans.py
cwave/wavefun.py
cwave-1.0.dist-info/DESCRIPTION.rst
cwave-1.0.dist-info/METADATA
cwave-1.0.dist-info/RECORD
cwave-1.0.dist-info/WHEEL
cwave-1.0.dist-info/metadata.json
cwave-1.0.dist-info/top_level.txt
