Metadata-Version: 2.0
Name: cwave
Version: 1.0
Summary: cwave
Home-page: UNKNOWN
Author: Davide Albanese
Author-email: davide.albanese@fmach.it
License: GPLv3
Platform: UNKNOWN
Classifier: Development Status :: 5 - Production/Stable
Classifier: Intended Audience :: Science/Research
Classifier: License :: OSI Approved :: GNU General Public License (GPL)
Classifier: Programming Language :: Python :: 2.7
Classifier: Programming Language :: Python :: 3
Classifier: Topic :: Scientific/Engineering
Classifier: Operating System :: OS Independent
Requires-Dist: numpy (>=1.7.0)
Requires-Dist: scipy (>=0.13)
Requires-Dist: six
